fooster_cron-0.9.0-py3.8-nspkg.pth
fooster/cron/__init__.py
fooster_cron-0.9.0.dist-info/LICENSE
fooster_cron-0.9.0.dist-info/METADATA
fooster_cron-0.9.0.dist-info/WHEEL
fooster_cron-0.9.0.dist-info/namespace_packages.txt
fooster_cron-0.9.0.dist-info/top_level.txt
fooster_cron-0.9.0.dist-info/RECORD
